lispi/.DS_Store
lispi/__init__.py
lispi/__main__.py
lispi/lispi.py
lispi/prompt.py
lispi/revealjs_template.py
lispi/slideEdit.py
lispi/text2audio.py
lispi/example/original_example.ipynb
lispi-0.0.10.dist-info/METADATA
lispi-0.0.10.dist-info/WHEEL
lispi-0.0.10.dist-info/entry_points.txt
lispi-0.0.10.dist-info/licenses/LICENSE
lispi-0.0.10.dist-info/RECORD
