Metadata-Version: 2.1
Name: lispi
Version: 0.0.10
Summary: `lispi` (Learning Interactive Slides and PIthon) is a python package for generating live notebooks where you can learn the content by listening to and reading from the slides at the same time you can write and execute yourown code from the slides in real time.
Project-URL: Homepage, https://github.com/B7M/lispi
Author-email: B7M <ibsnetwork001@gmail.com>
License: Copyright (c) 2023 The Python Packaging Authority
License-File: LICENSE
Keywords: code,live,notebook,py-scripts
Classifier: License :: OSI Approved :: MIT License
Classifier: Operating System :: OS Independent
Classifier: Programming Language :: Python :: 3
Requires-Python: >=3.7
Requires-Dist: click
Requires-Dist: gtts
Requires-Dist: jupyter
Requires-Dist: jupyterlab
Requires-Dist: nbconvert
Requires-Dist: nbformat
Requires-Dist: tomli; python_version < '3.11'
